{
	"name": "condsplit",
	"properties": {
		"type": "MappingDataFlow",
		"typeProperties": {
			"sources": [
				{
					"dataset": {
						"referenceName": "Parquet",
						"type": "DatasetReference"
					},
					"name": "condsplitstream"
				}
			],
			"sinks": [
				{
					"dataset": {
						"referenceName": "logdata_parquet_table",
						"type": "DatasetReference"
					},
					"name": "condsplit"
				}
			],
			"transformations": [
				{
					"name": "split1"
				}
			],
			"scriptLines": [
				"source(output(",
				"          Correlationid as string,",
				"          Operationname as string,",
				"          Status as string,",
				"          Eventcategory as string,",
				"          Level as string,",
				"          Time as string,",
				"          Subscription as string,",
				"          Eventinitiatedby as string,",
				"          Resourcetype as string,",
				"          Resourcegroup as string,",
				"          Resource as string",
				"     ),",
				"     allowSchemaDrift: true,",
				"     validateSchema: false,",
				"     ignoreNoFilesFound: false,",
				"     format: 'parquet') ~> condsplitstream",
				"condsplitstream split(Resourcegroup=='app-grp',",
				"     disjoint: false) ~> split1@(resourcegroupstream)",
				"split1@resourcegroupstream sink(allowSchemaDrift: true,",
				"     validateSchema: false,",
				"     input(",
				"          Correlationid as string,",
				"          Operationname as string,",
				"          Status as string,",
				"          Eventcategory as string,",
				"          Level as string,",
				"          Time as timestamp,",
				"          Subscription as string,",
				"          Eventinitiatedby as string,",
				"          Resourcetype as string,",
				"          Resourcegroup as string,",
				"          Resource as string,",
				"          FilePath as string",
				"     ),",
				"     deletable:false,",
				"     insertable:true,",
				"     updateable:false,",
				"     upsertable:false,",
				"     format: 'table',",
				"     skipDuplicateMapInputs: true,",
				"     skipDuplicateMapOutputs: true,",
				"     errorHandlingOption: 'stopOnFirstError',",
				"     mapColumn(",
				"          Correlationid,",
				"          Operationname,",
				"          Status,",
				"          Eventcategory,",
				"          Level,",
				"          Time,",
				"          Subscription,",
				"          Eventinitiatedby,",
				"          Resourcetype,",
				"          Resourcegroup,",
				"          Resource",
				"     )) ~> condsplit"
			]
		}
	}
}